.gitignore
LICENSE
README.md
enigme-runner.py
pyproject.toml
requirements.txt
enigme/__init__.py
enigme/cli.py
enigme/gridbased.py
enigme/numeric_puzzles.py
enigme/physics_puzzle_3d.py
enigme/seq_puzzle_3d.py
enigme/seqbased.py
enigme.egg-info/PKG-INFO
enigme.egg-info/SOURCES.txt
enigme.egg-info/dependency_links.txt
enigme.egg-info/entry_points.txt
enigme.egg-info/requires.txt
enigme.egg-info/top_level.txt
images/logo.png
images/logo.xcf