Metadata-Version: 2.4
Name: enigme
Version: 0.0.0
Summary: Python command line application for generating text based puzzles for training and testing machine learning models.
Author-email: John Hawkins <john@getting-data-science-done.com>
Project-URL: Homepage, https://github.com/john-hawkins/enigme
Project-URL: Documentation, http://enigme.readthedocs.io
Project-URL: Bug Tracker, https://github.com/john-hawkins/enigme/issues
Requires-Python: >=3.7
Requires-Dist: numpy
Requires-Dist: pandas
